tango/__init__.py
tango/client.py
tango/exceptions.py
tango/models.py
tango/shapes/__init__.py
tango/shapes/explicit_schemas.py
tango/shapes/factory.py
tango/shapes/generator.py
tango/shapes/models.py
tango/shapes/parser.py
tango/shapes/schema.py
tango/shapes/types.py
tango_python-0.2.0.dist-info/METADATA
tango_python-0.2.0.dist-info/WHEEL
tango_python-0.2.0.dist-info/licenses/LICENSE
tango_python-0.2.0.dist-info/RECORD
