Metadata-Version: 2.4
Name: tango-python
Version: 0.2.0
Summary: Python SDK for the Tango API
Project-URL: Homepage, https://github.com/makegov/tango-python
Project-URL: Documentation, https://docs.makegov.com/tango-python
Project-URL: Repository, https://github.com/makegov/tango-python
Project-URL: Issues, https://github.com/makegov/tango-python/issues
Author-email: MakeGov <tango@makegov.com>
License: MIT License
License-File: LICENSE
Keywords: api,contracts,government,sdk,tango
Classifier: Development Status :: 4 - Beta
Classifier: Intended Audience :: Developers
Classifier: License :: OSI Approved :: MIT License
Classifier: Operating System :: OS Independent
Classifier: Programming Language :: Python :: 3
Classifier: Programming Language :: Python :: 3.12
Classifier: Programming Language :: Python :: 3.13
Requires-Python: >=3.12
Requires-Dist: httpx>=0.27.0
Provides-Extra: dev
Requires-Dist: mypy>=1.8; extra == 'dev'
Requires-Dist: pytest-cov>=4.1; extra == 'dev'
Requires-Dist: pytest-httpx>=0.30.0; extra == 'dev'
Requires-Dist: pytest-recording>=0.13.0; extra == 'dev'
Requires-Dist: pytest>=8.0; extra == 'dev'
Requires-Dist: python-dotenv>=1.0.0; extra == 'dev'
Requires-Dist: pyyaml>=6.0; extra == 'dev'
Requires-Dist: ruff>=0.3.0; extra == 'dev'
Provides-Extra: notebooks
Requires-Dist: ipykernel>=6.25.0; extra == 'notebooks'
Requires-Dist: jupyter>=1.0.0; extra == 'notebooks'
